yagni/__init__.py
yagni/pydantic/__init__.py
yagni/pydantic/types.py
yagni/time/__init__.py
yagni-0.0.4.dist-info/LICENSE
yagni-0.0.4.dist-info/METADATA
yagni-0.0.4.dist-info/WHEEL
yagni-0.0.4.dist-info/top_level.txt
yagni-0.0.4.dist-info/RECORD
